Metadata-Version: 2.1
Name: discord-logging-fork1
Version: 1.0
Summary: Transfer logs acquired by logging module to discord with webhook!
Home-page: https://github.com/AlexNovikovRussian/discord_logging
Author: kadyk_lesha
Author-email: novikovprjjects@gmail.com
License: UNKNOWN
Platform: UNKNOWN
Classifier: Programming Language :: Python :: 3.8
Classifier: License :: OSI Approved :: MIT License
Classifier: Operating System :: OS Independent
